abir/__init__.py
abir/attributes.py
abir/core.py
abir/environ.py
abir/yaml.py
abir-0.1.4.dist-info/WHEEL
abir-0.1.4.dist-info/METADATA
abir-0.1.4.dist-info/RECORD
