Metadata-Version: 2.1
Name: abir
Version: 0.1.4
Summary: python project load config from yaml and environment.
Home-page: https://github.com/jioone/abir
License: MIT
Keywords: pyyaml,django,django config yaml,python configure
Author: Jone
Author-email: zjhjin@live.com
Requires-Python: >=3.6,<4.0
Classifier: License :: OSI Approved :: MIT License
Classifier: Programming Language :: Python :: 3
Classifier: Programming Language :: Python :: 3.10
Classifier: Programming Language :: Python :: 3.6
Classifier: Programming Language :: Python :: 3.7
Classifier: Programming Language :: Python :: 3.8
Classifier: Programming Language :: Python :: 3.9
Requires-Dist: PyYAML (>=6.0,<7.0)
Project-URL: Repository, https://github.com/jioone/abir
